README.md
setup.py
RobotLib/Bus_Servo_Lib.py
RobotLib/Bus_Servo_Lib_Test.py
RobotLib/Bus_Servo_Motion.py
RobotLib/CameralLib.py
RobotLib/Pwm_Servo_Lib.py
RobotLib/Pwm_Servo_Motion.py
RobotLib/Pwm_Servo_Motion_Bak.py
RobotLib/__init__.py
RobotLib/myzabbix.py
RobotLib/serial_common1.py
RobotLib/serial_common2.py
RobotLib/serial_test.py
RobotLib/test.py
RobotLib.egg-info/PKG-INFO
RobotLib.egg-info/SOURCES.txt
RobotLib.egg-info/dependency_links.txt
RobotLib.egg-info/requires.txt
RobotLib.egg-info/top_level.txt