Metadata-Version: 2.1
Name: RobotLib
Version: 1.0.0
Summary: 机器人控制系统的通用工具包
Home-page: https://www.haisheng666.xin/user_system/login?next=/robot/
Author: Hanson
Author-email: 821058392@qq.com
License: UNKNOWN
Platform: UNKNOWN
Classifier: Programming Language :: Python :: 3
Classifier: License :: OSI Approved :: MIT License
Classifier: Operating System :: OS Independent
Requires-Python: >=3.7
